chardif/__init__.py
chardif/_version.py
chardif/core.py
chardif-0.1.3.dist-info/LICENSE
chardif-0.1.3.dist-info/METADATA
chardif-0.1.3.dist-info/WHEEL
chardif-0.1.3.dist-info/top_level.txt
chardif-0.1.3.dist-info/RECORD
