Metadata-Version: 2.1
Name: chardif
Version: 0.1.3
Summary: Print per-character string diffs to terminal w/ Python
Home-page: https://github.com/shaypal5/chardif
Author: Shay Palachy
Author-email: shay.palachy@gmail.com
License: MIT
Keywords: diff,wasabi,chardiff
Platform: linux
Platform: osx
Platform: windows
Classifier: Development Status :: 4 - Beta
Classifier: License :: OSI Approved :: MIT License
Classifier: Programming Language :: Python
Classifier: Programming Language :: Python :: 3
Classifier: Programming Language :: Python :: 3.6
Classifier: Programming Language :: Python :: 3.7
Classifier: Programming Language :: Python :: 3.8
Classifier: Programming Language :: Python :: 3.9
Classifier: Topic :: Software Development :: Libraries
Classifier: Topic :: Software Development :: Libraries :: Python Modules
Classifier: Topic :: Utilities
Classifier: Topic :: Other/Nonlisted Topic
Classifier: Intended Audience :: Developers
Requires-Dist: wasabi
Provides-Extra: test
Requires-Dist: pytest ; extra == 'test'
Requires-Dist: coverage ; extra == 'test'
Requires-Dist: pytest-cov ; extra == 'test'
